Andrutil/MachineLearning.py
Andrutil/Misc.py
Andrutil/Multiprocessor.py
Andrutil/Neuroscience.py
Andrutil/ObserverObservable.py
Andrutil/Watchdog.py
Andrutil/__init__.py
Andrutil-0.1.dist-info/METADATA
Andrutil-0.1.dist-info/WHEEL
Andrutil-0.1.dist-info/top_level.txt
Andrutil-0.1.dist-info/RECORD
