Metadata-Version: 2.1
Name: Andrutil
Version: 0.1
Summary: packages=setuptools.find_packages(),
Home-page: https://github.com/Adrang/Andrutil
Author: Adrang
Author-email: andrew@andrewtfesta.com
License: UNKNOWN
Platform: UNKNOWN
Classifier: Programming Language :: Python :: 3
Classifier: License :: OSI Approved :: MIT License
Classifier: Operating System :: OS Independent
Requires-Python: >=3.7
